excel_util/__init__.py
excel_util/mk_book.py
excel_insert_max-0.0.2.dist-info/LICENSE
excel_insert_max-0.0.2.dist-info/METADATA
excel_insert_max-0.0.2.dist-info/WHEEL
excel_insert_max-0.0.2.dist-info/top_level.txt
excel_insert_max-0.0.2.dist-info/RECORD
