Metadata-Version: 2.1
Name: excel-insert-max
Version: 0.0.2
Summary: insert excel book, base xlwt
Home-page: https://github.com/pypa/sampleproject
Author: max
Author-email: ma_ke_min@163.com
License: UNKNOWN
Project-URL: Bug Tracker, https://github.com/pypa/sampleproject/issues
Platform: UNKNOWN
Classifier: Programming Language :: Python :: 3
Classifier: License :: OSI Approved :: MIT License
Classifier: Operating System :: OS Independent
Requires-Python: >=3.5
License-File: LICENSE
